{
    "ConfigVersion": 22,
    "ID": 14,
    "Type": 1,
    "Title": "Bienvenido a IronZone",
    "Descriptions": [
        "Bienvenido. Me llaman K, de los Peregrinos. No te pido nada, solo que no causes problemas.",
        "Patter sigue ayudando a los supervivientes desde las ruinas del antiguo asentamiento de los Peregrinos. Fue destruido hace poco, pero se negó a abandonarlo. Ve a verlo; aún tiene trabajo para alguien dispuesto a echar una mano.",
        "Green Mountain es nuestro hogar. Aquí siempre encontrarás refugio si vienes en paz."
    ],
    "ObjectiveText": "Visita el campamento en la ubicaciÃƒÆ’Ã‚Â³n marcada.",
    "FollowUpQuest": -1,
    "Repeatable": 0,
    "IsDailyQuest": 0,
    "IsWeeklyQuest": 0,
    "CancelQuestOnPlayerDeath": 0,
    "Autocomplete": 1,
    "IsGroupQuest": 0,
    "ObjectSetFileName": "",
    "QuestItems": [],
    "Rewards": [
        {
            "ClassName": "ChernarusMap",
            "Amount": 1,
            "Attachments": [],
            "DamagePercent": 0,
            "HealthPercent": 0,
            "QuestID": -1,
            "Chance": 1
        }
    ],
    "NeedToSelectReward": 0,
    "RandomReward": 0,
    "RandomRewardAmount": 0,
    "RewardsForGroupOwnerOnly": 0,
    "RewardBehavior": 0,
    "QuestGiverIDs": [],
    "QuestTurnInIDs": [
        1
    ],
    "IsAchievement": 0,
    "Objectives": [
        {
            "ConfigVersion": 28,
            "ID": 3,
            "ObjectiveType": 3
        }
    ],
    "QuestColor": 0,
    "ReputationReward": 20,
    "ReputationRequirement": 0,
    "PreQuestIDs": [],
    "RequiredFaction": "",
    "FactionReward": "",
    "PlayerNeedQuestItems": 1,
    "DeleteQuestItems": 1,
    "SequentialObjectives": 0,
    "FactionReputationRequirements": {},
    "FactionReputationRewards": {},
    "SuppressQuestLogOnCompetion": 0,
    "Active": 1
}